pyneuro_autoalign/__init__.py
pyneuro_autoalign/autoalign.py
pyneuro_autoalign/autoalign_OLD.py
pyneuro_io/__init__.py
pyneuro_io/amiraparsing.py
pyneuro_io/hoc_reader.py
pyneuro_io/landmarkwriter.py
pyneuro_io/scalar_field.py
pyneuro_io/spatialgraphwriter.py
pyneuro_io/surfacewriter.py
pyneuro_reconstruction/__init__.py
pyneuro_reconstruction/centerer.py
pyneuro_reconstruction/dijkstra.py
pyneuro_reconstruction/dijkstra_grid.py
pyneuro_reconstruction/flatmaprep.py
pyneuro_reconstruction/flatmaptransform.py
pyneuro_reconstruction/generate_averagesurface.py
pyneuro_reconstruction/icp.py
pyneuro_reconstruction/mesh_surface.py
pyneuro_reconstruction/scaledown.py
pyneuro_reconstruction/triangleresampler.py
pyneuro_reconstruction/triangleresampler_2.py
pyneuro_reconstruction/triangleresampler_old.py
pyneuroreg-0.2.dist-info/METADATA
pyneuroreg-0.2.dist-info/RECORD
pyneuroreg-0.2.dist-info/WHEEL
pyneuroreg-0.2.dist-info/top_level.txt
