Metadata-Version: 2.1
Name: pyneuroreg
Version: 0.2
Summary: pyneuroreg contains all the scripts from my master project of creating the reference frame of rat motor cortex
Home-page: UNKNOWN
Author: Peter Park
Author-email: peterpark828@gmail.com
License: MIT
Platform: UNKNOWN
